{
  "content": null,
  "embeds": [
    {
      "title": "Stato server Minecraft:",
      "color": 65300,
      "fields": [
        {
          "name": "Stato server:",
          "value": ":white_check_mark: ONLINE"
        },
        {
          "name": "Indirizzo IP:",
          "value": ":signal_strength: %s"
        },
        {
          "name": "Whitelist:",
          "value": ":lock: Chiedi aggiunta in **#:video_game:games**"
        }
      ],
      "footer": {
        "text": "Ultimo aggiornamento"
      },
      "timestamp": "%s"
    }
  ]
}